td_ml_activation_stats/__init__.py
td_ml_activation_stats/activation_stats.py
td_ml_activation_stats-0.0.6.dist-info/LICENSE
td_ml_activation_stats-0.0.6.dist-info/METADATA
td_ml_activation_stats-0.0.6.dist-info/WHEEL
td_ml_activation_stats-0.0.6.dist-info/top_level.txt
td_ml_activation_stats-0.0.6.dist-info/RECORD
